BiliDrive/__init__.py
BiliDrive/__main__.py
BiliDrive/bilibili.py
BiliDrive-2019.12.22.dist-info/LICENSE
BiliDrive-2019.12.22.dist-info/METADATA
BiliDrive-2019.12.22.dist-info/WHEEL
BiliDrive-2019.12.22.dist-info/entry_points.txt
BiliDrive-2019.12.22.dist-info/top_level.txt
BiliDrive-2019.12.22.dist-info/RECORD
